AUTHORS
CHANGELOG
LICENSE
MANIFEST.in
README.rst
setup.cfg
setup.py
foreman/__init__.py
foreman/client.py
foreman/definitions/1.15.0-v1.json
foreman/definitions/1.4.2-v1.json
foreman/definitions/1.4.2-v2.json
foreman/definitions/1.5.0-v1.json
foreman/definitions/1.5.0-v2.json
foreman/definitions/1.6.3-v1.json
foreman/definitions/1.6.3-v2.json
foreman/definitions/1.7.1-v1.json
foreman/definitions/1.7.1-v2.json
foreman/definitions/1.7.2-v1.json
foreman/definitions/1.7.2-v2.json
foreman/definitions/1.9.2-v2.json
python_foreman.egg-info/PKG-INFO
python_foreman.egg-info/SOURCES.txt
python_foreman.egg-info/dependency_links.txt
python_foreman.egg-info/requires.txt
python_foreman.egg-info/top_level.txt