Metadata-Version: 1.1
Name: python-foreman
Version: 0.4.20
Summary: Simple low-level client library to access the Foreman API
Home-page: https://github.com/david-caro/python-foreman
Author: David Caro
Author-email: david@dcaro.es
License: GPLv2
Platform: UNKNOWN
Classifier: Intended Audience :: Developers
Classifier: Intended Audience :: Information Technology
Classifier: License :: OSI Approved :: GNU General Public License v2 (GPLv2)
Classifier: Operating System :: OS Independent
Classifier: Programming Language :: Python
Classifier: Programming Language :: Python :: 2.7
Classifier: Programming Language :: Python :: 3.4
